cache/__init__.py
cache/filecache.py
adt_cache-0.0.14.dist-info/LICENSE
adt_cache-0.0.14.dist-info/METADATA
adt_cache-0.0.14.dist-info/WHEEL
adt_cache-0.0.14.dist-info/top_level.txt
adt_cache-0.0.14.dist-info/RECORD
