Metadata-Version: 2.1
Name: adt-cache
Version: 0.0.14
Summary: abstract cache with in memory cache or redis (sentinel)
Home-page: https://github.com/cheddars/pypi_adt_cache
Author: cheddars
Author-email: nezahrish@gmail.com
License: MIT
Platform: UNKNOWN
Classifier: Programming Language :: Python :: 3
Classifier: License :: OSI Approved :: MIT License
Classifier: Operating System :: OS Independent
License-File: LICENSE
